sealcore.cpython-310-x86_64-linux-gnu.so
sealgw/__init__.py
sealgw/seal.py
sealgw/calculation/__init__.py
sealgw/calculation/localization.py
sealgw/calculation/multiorder4fits.py
sealgw/simulation/__init__.py
sealgw/simulation/generating_data.py
sealgw/simulation/prior_fitting.py
sealgw/simulation/sealinterferometers.py
sealgw-0.0.6.dist-info/METADATA
sealgw-0.0.6.dist-info/WHEEL
sealgw-0.0.6.dist-info/top_level.txt
sealgw-0.0.6.dist-info/RECORD
sealgw.libs/libopenblasp-r0-230bbc78.3.25.so
sealgw.libs/libgomp-92112f98.so.1.0.0
sealgw.libs/libfftw3-a55d9fb4.so.3.6.10
sealgw.libs/libcfitsio-eb5c8d2a.so.10.4.3.1
sealgw.libs/libgsl-8ef43374.so.25.1.0
sealgw.libs/libk5crypto-8ed29d0b.so.3.1
sealgw.libs/libkeyutils-eda72732.so.1.9
sealgw.libs/libgssapi_krb5-ab8a4563.so.2.2
sealgw.libs/libcrypto-4df1cde0.so.3
sealgw.libs/libssl-3b9265a1.so.3
sealgw.libs/libssh2-fb7f9816.so.1.0.1
sealgw.libs/libquadmath-9f3c86f6.so.0.0.0
sealgw.libs/libbz2-60d52da8.so.1.0.8
sealgw.libs/libnghttp2-118fa687.so.14.25.1
sealgw.libs/liblal-4ea34287.so.20.3.2
sealgw.libs/libcom_err-38b1f41b.so.3.0
sealgw.libs/libgfortran-2ef2c681.so.5.0.0
sealgw.libs/libkrb5support-1dde2c2b.so.0.1
sealgw.libs/libkrb5-7e4bf988.so.3.3
sealgw.libs/libchealpix-106287a3.so.0.0.0
sealgw.libs/libcurl-5c1e3723.so.4.8.0
sealgw.libs/libfftw3f-d1287f30.so.3.6.10
sealgw.libs/libzstd-52a5ab61.so.1.5.5
